md_babel_py/__init__.py
md_babel_py/cache.py
md_babel_py/cli.py
md_babel_py/config.py
md_babel_py/default_config.json
md_babel_py/exceptions.py
md_babel_py/executor.py
md_babel_py/parser.py
md_babel_py/session.py
md_babel_py/session_server.py
md_babel_py/types.py
md_babel_py/writer.py
md_babel_py-1.1.1.dist-info/licenses/LICENSE
md_babel_py-1.1.1.dist-info/METADATA
md_babel_py-1.1.1.dist-info/WHEEL
md_babel_py-1.1.1.dist-info/entry_points.txt
md_babel_py-1.1.1.dist-info/top_level.txt
md_babel_py-1.1.1.dist-info/RECORD
