Metadata-Version: 2.4
Name: md-babel-py
Version: 1.1.1
Summary: Execute code blocks in markdown files with session support
Author-email: Ivan Nikolic <lesh@mm.st>
License-Expression: MIT
Requires-Python: >=3.10
License-File: LICENSE
Provides-Extra: dev
Requires-Dist: pytest; extra == "dev"
Requires-Dist: ruff; extra == "dev"
Requires-Dist: mypy; extra == "dev"
Provides-Extra: matplotlib
Requires-Dist: matplotlib; extra == "matplotlib"
Requires-Dist: numpy; extra == "matplotlib"
Dynamic: license-file
